{
  "__inputs": [
    {
      "name": "DS_PROMETHEUS",
      "label": "prometheus",
      "description": "",
      "type": "datasource",
      "pluginId": "prometheus",
      "pluginName": "Prometheus"
    }
  ],
  "__elements": {},
  "__requires": [
    {
      "type": "panel",
      "id": "bargauge",
      "name": "Bar gauge",
      "version": ""
    },
    {
      "type": "panel",
      "id": "gauge",
      "name": "Gauge",
      "version": ""
    },
    {
      "type": "grafana",
      "id": "grafana",
      "name": "Grafana",
      "version": "12.2.0"
    },
    {
      "type": "datasource",
      "id": "prometheus",
      "name": "Prometheus",
      "version": "1.0.0"
    }
  ],
  "annotations": {
    "list": [
      {
        "builtIn": 1,
        "datasource": {
          "type": "grafana",
          "uid": "-- Grafana --"
        },
        "enable": true,
        "hide": true,
        "iconColor": "rgba(0, 211, 255, 1)",
        "name": "Annotations & Alerts",
        "type": "dashboard"
      }
    ]
  },
  "description": "VerneMQTT broker metrics on k3s",
  "editable": true,
  "fiscalYearStartMonth": 0,
  "graphTooltip": 0,
  "id": null,
  "links": [],
  "panels": [
    {
      "datasource": {
        "type": "prometheus",
        "uid": "${DS_PROMETHEUS}"
      },
      "fieldConfig": {
        "defaults": {
          "color": {
            "mode": "thresholds"
          },
          "mappings": [],
          "thresholds": {
            "mode": "absolute",
            "steps": [
              {
                "color": "green",
                "value": 0
              },
              {
                "color": "green",
                "value": 80
              }
            ]
          }
        },
        "overrides": []
      },
      "gridPos": {
        "h": 7,
        "w": 7,
        "x": 0,
        "y": 0
      },
      "id": 4,
      "options": {
        "minVizHeight": 129,
        "minVizWidth": 75,
        "orientation": "horizontal",
        "reduceOptions": {
          "calcs": [
            "lastNotNull"
          ],
          "fields": "",
          "values": false
        },
        "showThresholdLabels": false,
        "showThresholdMarkers": true,
        "sizing": "auto"
      },
      "pluginVersion": "12.2.0",
      "targets": [
        {
          "datasource": {
            "type": "prometheus",
            "uid": "${DS_PROMETHEUS}"
          },
          "editorMode": "builder",
          "expr": "sum(vernemq_bytes_received{job=\"vernemq-metrics\"})",
          "instant": false,
          "legendFormat": "__auto",
          "range": true,
          "refId": "A"
        }
      ],
      "title": "Bytes Received (total)",
      "type": "gauge"
    },
    {
      "datasource": {
        "type": "prometheus",
        "uid": "${DS_PROMETHEUS}"
      },
      "fieldConfig": {
        "defaults": {
          "color": {
            "mode": "thresholds"
          },
          "mappings": [],
          "thresholds": {
            "mode": "absolute",
            "steps": [
              {
                "color": "light-purple",
                "value": 0
              },
              {
                "color": "green",
                "value": 100
              },
              {
                "color": "super-light-yellow",
                "value": 500
              },
              {
                "color": "yellow",
                "value": 1000
              },
              {
                "color": "orange",
                "value": 2000
              },
              {
                "color": "super-light-red",
                "value": 3000
              },
              {
                "color": "red",
                "value": 5000
              }
            ]
          }
        },
        "overrides": []
      },
      "gridPos": {
        "h": 7,
        "w": 10,
        "x": 7,
        "y": 0
      },
      "id": 7,
      "options": {
        "minVizHeight": 129,
        "minVizWidth": 75,
        "orientation": "horizontal",
        "reduceOptions": {
          "calcs": [
            "lastNotNull"
          ],
          "fields": "",
          "values": false
        },
        "showThresholdLabels": false,
        "showThresholdMarkers": true,
        "sizing": "auto"
      },
      "pluginVersion": "12.2.0",
      "targets": [
        {
          "datasource": {
            "type": "prometheus",
            "uid": "${DS_PROMETHEUS}"
          },
          "editorMode": "builder",
          "expr": "sum(vernemq_active_mqtt_connections{job=\"vernemq-metrics\", pod=~\"vernemq-broker-.*\"})",
          "instant": false,
          "legendFormat": "__auto",
          "range": true,
          "refId": "A"
        }
      ],
      "title": "Total Concurrent Connections",
      "type": "gauge"
    },
    {
      "datasource": {
        "type": "prometheus",
        "uid": "${DS_PROMETHEUS}"
      },
      "fieldConfig": {
        "defaults": {
          "color": {
            "mode": "thresholds"
          },
          "mappings": [],
          "thresholds": {
            "mode": "absolute",
            "steps": [
              {
                "color": "green",
                "value": 0
              },
              {
                "color": "green",
                "value": 80
              }
            ]
          }
        },
        "overrides": []
      },
      "gridPos": {
        "h": 7,
        "w": 7,
        "x": 17,
        "y": 0
      },
      "id": 6,
      "options": {
        "minVizHeight": 129,
        "minVizWidth": 75,
        "orientation": "horizontal",
        "reduceOptions": {
          "calcs": [
            "lastNotNull"
          ],
          "fields": "",
          "values": false
        },
        "showThresholdLabels": false,
        "showThresholdMarkers": true,
        "sizing": "auto"
      },
      "pluginVersion": "12.2.0",
      "targets": [
        {
          "datasource": {
            "type": "prometheus",
            "uid": "${DS_PROMETHEUS}"
          },
          "editorMode": "builder",
          "expr": "sum(vernemq_bytes_sent{job=\"vernemq-metrics\"})",
          "instant": false,
          "legendFormat": "__auto",
          "range": true,
          "refId": "A"
        }
      ],
      "title": "Bytes Sent (total)",
      "type": "gauge"
    },
    {
      "datasource": {
        "type": "prometheus",
        "uid": "${DS_PROMETHEUS}"
      },
      "fieldConfig": {
        "defaults": {
          "color": {
            "mode": "thresholds"
          },
          "mappings": [],
          "thresholds": {
            "mode": "absolute",
            "steps": [
              {
                "color": "green",
                "value": 0
              },
              {
                "color": "red",
                "value": 80
              }
            ]
          }
        },
        "overrides": []
      },
      "gridPos": {
        "h": 9,
        "w": 9,
        "x": 0,
        "y": 7
      },
      "id": 2,
      "options": {
        "displayMode": "gradient",
        "legend": {
          "calcs": [],
          "displayMode": "list",
          "placement": "bottom",
          "showLegend": false
        },
        "maxVizHeight": 300,
        "minVizHeight": 16,
        "minVizWidth": 8,
        "namePlacement": "auto",
        "orientation": "auto",
        "reduceOptions": {
          "calcs": [
            "lastNotNull"
          ],
          "fields": "",
          "values": false
        },
        "showUnfilled": true,
        "sizing": "auto",
        "valueMode": "color"
      },
      "pluginVersion": "12.2.0",
      "targets": [
        {
          "datasource": {
            "type": "prometheus",
            "uid": "${DS_PROMETHEUS}"
          },
          "editorMode": "builder",
          "expr": "vernemq_active_mqtt_connections{job=\"vernemq-metrics\", pod=~\"vernemq-broker-.*\"}",
          "instant": false,
          "legendFormat": "__auto",
          "range": true,
          "refId": "A"
        }
      ],
      "title": "Active MQTT connections",
      "type": "bargauge"
    },
    {
      "datasource": {
        "type": "prometheus",
        "uid": "${DS_PROMETHEUS}"
      },
      "fieldConfig": {
        "defaults": {
          "color": {
            "mode": "continuous-GrYlRd"
          },
          "mappings": [],
          "thresholds": {
            "mode": "absolute",
            "steps": [
              {
                "color": "green",
                "value": 0
              },
              {
                "color": "red",
                "value": 80
              }
            ]
          }
        },
        "overrides": []
      },
      "gridPos": {
        "h": 9,
        "w": 15,
        "x": 9,
        "y": 7
      },
      "id": 5,
      "options": {
        "minVizHeight": 75,
        "minVizWidth": 75,
        "orientation": "auto",
        "reduceOptions": {
          "calcs": [
            "lastNotNull"
          ],
          "fields": "",
          "values": false
        },
        "showThresholdLabels": false,
        "showThresholdMarkers": false,
        "sizing": "auto"
      },
      "pluginVersion": "12.2.0",
      "targets": [
        {
          "datasource": {
            "type": "prometheus",
            "uid": "${DS_PROMETHEUS}"
          },
          "editorMode": "builder",
          "expr": "sum by(node) (rate(vernemq_mqtt_publish_received{job=\"vernemq-metrics\"}[1h])) + (sum by(node) (rate(vernemq_mqtt_publish_sent{job=\"vernemq-metrics\"}[1h])))",
          "hide": false,
          "instant": false,
          "legendFormat": "__auto",
          "range": true,
          "refId": "A"
        }
      ],
      "title": "Published Messages rate",
      "type": "gauge"
    },
    {
      "datasource": {
        "type": "prometheus",
        "uid": "${DS_PROMETHEUS}"
      },
      "fieldConfig": {
        "defaults": {
          "color": {
            "mode": "thresholds"
          },
          "mappings": [],
          "thresholds": {
            "mode": "absolute",
            "steps": [
              {
                "color": "green",
                "value": 0
              },
              {
                "color": "light-blue",
                "value": 80
              }
            ]
          }
        },
        "overrides": []
      },
      "gridPos": {
        "h": 13,
        "w": 11,
        "x": 0,
        "y": 16
      },
      "id": 1,
      "options": {
        "displayMode": "lcd",
        "legend": {
          "calcs": [],
          "displayMode": "list",
          "placement": "bottom",
          "showLegend": true
        },
        "maxVizHeight": 300,
        "minVizHeight": 16,
        "minVizWidth": 8,
        "namePlacement": "top",
        "orientation": "horizontal",
        "reduceOptions": {
          "calcs": [
            "lastNotNull"
          ],
          "fields": "",
          "values": false
        },
        "showUnfilled": true,
        "sizing": "manual",
        "valueMode": "text"
      },
      "pluginVersion": "12.2.0",
      "targets": [
        {
          "datasource": {
            "type": "prometheus",
            "uid": "${DS_PROMETHEUS}"
          },
          "editorMode": "builder",
          "expr": "vernemq_bytes_received{job=\"vernemq-metrics\", pod!~\"vernemq-broker-.*\"}",
          "instant": false,
          "legendFormat": "__auto",
          "range": true,
          "refId": "A"
        }
      ],
      "title": "Bytes Received per pods",
      "type": "bargauge"
    },
    {
      "datasource": {
        "type": "prometheus",
        "uid": "${DS_PROMETHEUS}"
      },
      "fieldConfig": {
        "defaults": {
          "color": {
            "mode": "thresholds"
          },
          "mappings": [],
          "thresholds": {
            "mode": "absolute",
            "steps": [
              {
                "color": "green",
                "value": 0
              },
              {
                "color": "blue",
                "value": 80
              }
            ]
          }
        },
        "overrides": [
          {
            "__systemRef": "hideSeriesFrom",
            "matcher": {
              "id": "byNames",
              "options": {
                "mode": "exclude",
                "names": [
                  "{__name__=\"vernemq_bytes_sent\", instance=\"10.42.0.110:8888\", job=\"vernemq-metrics\", node=\"VerneMQ@10.42.0.110\", pod=\"vernemq-broker-5585cd6d-gqxrr\"}",
                  "{__name__=\"vernemq_bytes_sent\", instance=\"10.42.0.111:8888\", job=\"vernemq-metrics\", node=\"VerneMQ@10.42.0.111\", pod=\"vernemq-broker-5585cd6d-vg2qr\"}",
                  "{__name__=\"vernemq_bytes_sent\", instance=\"10.42.0.113:8888\", job=\"vernemq-metrics\", node=\"VerneMQ@10.42.0.113\", pod=\"vernemq-broker-5585cd6d-lstmh\"}",
                  "{__name__=\"vernemq_bytes_sent\", instance=\"10.42.0.114:8888\", job=\"vernemq-metrics\", node=\"VerneMQ@10.42.0.114\", pod=\"vernemq-broker-5585cd6d-pckfl\"}",
                  "{__name__=\"vernemq_bytes_sent\", instance=\"vernemq-broker.verne.svc.cluster.local:8888\", job=\"vernemq-metrics\", node=\"VerneMQ@10.42.0.110\"}",
                  "{__name__=\"vernemq_bytes_sent\", instance=\"vernemq-broker.verne.svc.cluster.local:8888\", job=\"vernemq-metrics\", node=\"VerneMQ@10.42.0.111\"}",
                  "{__name__=\"vernemq_bytes_sent\", instance=\"vernemq-broker.verne.svc.cluster.local:8888\", job=\"vernemq-metrics\", node=\"VerneMQ@10.42.0.113\"}",
                  "{__name__=\"vernemq_bytes_sent\", instance=\"vernemq-broker.verne.svc.cluster.local:8888\", job=\"vernemq-metrics\", node=\"VerneMQ@10.42.0.114\"}",
                  "{__name__=\"vernemq_bytes_sent\", instance=\"vernemq-broker.verne.svc.cluster.local:8888\", job=\"vernemq-metrics\", node=\"VerneMQ@10.42.0.118\"}"
                ],
                "prefix": "All except:",
                "readOnly": true
              }
            },
            "properties": []
          }
        ]
      },
      "gridPos": {
        "h": 13,
        "w": 13,
        "x": 11,
        "y": 16
      },
      "id": 3,
      "options": {
        "displayMode": "lcd",
        "legend": {
          "calcs": [],
          "displayMode": "list",
          "placement": "bottom",
          "showLegend": true
        },
        "maxVizHeight": 300,
        "minVizHeight": 48,
        "minVizWidth": 8,
        "namePlacement": "top",
        "orientation": "horizontal",
        "reduceOptions": {
          "calcs": [
            "lastNotNull"
          ],
          "fields": "",
          "values": false
        },
        "showUnfilled": true,
        "sizing": "manual",
        "valueMode": "text"
      },
      "pluginVersion": "12.2.0",
      "targets": [
        {
          "datasource": {
            "type": "prometheus",
            "uid": "${DS_PROMETHEUS}"
          },
          "editorMode": "code",
          "expr": "vernemq_bytes_sent{job=\"vernemq-metrics\", pod=~\"vernemq-broker-.*\"}",
          "instant": false,
          "legendFormat": "__auto",
          "range": true,
          "refId": "A"
        }
      ],
      "title": "Bytes Sent per pods",
      "type": "bargauge"
    }
  ],
  "refresh": "10s",
  "schemaVersion": 42,
  "tags": [
    "vernemq",
    "kubernetes"
  ],
  "templating": {
    "list": []
  },
  "time": {
    "from": "now-1h",
    "to": "now"
  },
  "timepicker": {},
  "timezone": "browser",
  "title": "VerneMQ Metrics (Custom)",
  "uid": "adsk8gz",
  "version": 19,
  "weekStart": ""
}